setup.py
bin/CompareManPagesScript.py
bin/__init__.py
compare_man_pages_from_two_folders/CompareManPages.py
compare_man_pages_from_two_folders/ConfigurationByUser.py
compare_man_pages_from_two_folders/__init__.py
compare_man_pages_from_two_folders.egg-info/PKG-INFO
compare_man_pages_from_two_folders.egg-info/SOURCES.txt
compare_man_pages_from_two_folders.egg-info/dependency_links.txt
compare_man_pages_from_two_folders.egg-info/not-zip-safe
compare_man_pages_from_two_folders.egg-info/requires.txt
compare_man_pages_from_two_folders.egg-info/top_level.txt
compare_man_pages_from_two_folders/man_page_PyXB/__init__.py
compare_man_pages_from_two_folders/man_page_PyXB/_base.py
compare_man_pages_from_two_folders/man_page_PyXB/alarm_description.py
compare_man_pages_from_two_folders/man_page_PyXB/com/__init__.py
compare_man_pages_from_two_folders/man_page_PyXB/com/nokia/__init__.py
compare_man_pages_from_two_folders/man_page_PyXB/com/nokia/oss/__init__.py
compare_man_pages_from_two_folders/man_page_PyXB/com/nokia/oss/fm/__init__.py
compare_man_pages_from_two_folders/man_page_PyXB/com/nokia/oss/fm/_types.py