Metadata-Version: 1.1
Name: compare-man-pages-from-two-folders
Version: 1.0.0.dev1
Summary: A tool used to compare man pages with same name from separate folders
Home-page: http://github.com/storborg/compare_man_pages_from_two_folders
Author: Corey Lin
Author-email: 514971757@qq.com
License: MIT
Platform: UNKNOWN
Classifier: Programming Language :: Python :: 2.7
